zangshencc/__init__.py
zangshencc/browser.py
zangshencc/element.py
zangshencc/wait.py
zangshencc-0.1.1.dist-info/METADATA
zangshencc-0.1.1.dist-info/WHEEL
zangshencc-0.1.1.dist-info/top_level.txt
zangshencc-0.1.1.dist-info/RECORD
