Metadata-Version: 2.4
Name: zangshencc
Version: 0.1.1
Summary: zangshencc
Author-email: cc <zangshencc@gmail.com>
Requires-Python: >=3.9
Requires-Dist: DrissionPage>=4.0
